{
    "services": {
        "LaunchPage": {
            "adapter": {
                "config": {
                    "groups": [
                        {
                            "id": "emptyhome",
                            "isVisible": false,
                            "isDefaultGroup": true,
                            "tiles": []
                        },
                        {
                            "id": "extensions",
                            "title": "Odata Prototype Apps",
                            "isVisible": true,
                            "isGroupLocked": false,
                            "tiles": [
                                {
                                    "id": "reusecomp",
                                    "tileType": "sap.ushell.ui.tile.StaticTile",
                                    "properties": {
                                        "title": "Reuse Component",
                                        "info": "",
                                        "icon": "sap-icon://Fiori2/F0006",
                                        "targetURL": "#Reusecomp-manage"
                                    }
                                },
                                {
                                    "id": "compconsumer",
                                    "tileType": "sap.ushell.ui.tile.StaticTile",
                                    "properties": {
                                        "title": "Component Consumer",
                                        "info": "",
                                        "icon": "sap-icon://Fiori2/F0006",
                                        "targetURL": "#Consumer-manage"
                                    }
                                },
                                {
                                    "id": "compconsumer02",
                                    "tileType": "sap.ushell.ui.tile.StaticTile",
                                    "properties": {
                                        "title": "Component Consumer 02",
                                        "info": "",
                                        "icon": "sap-icon://Fiori2/F0006",
                                        "targetURL": "#Consumer02-manage"
                                    }
                                }
                            ]
                        }
                    ]
                }
            }
        },
        "NavTargetResolution": {
            "config": {
                "enableClientSideTargetResolution": true
            }
        },
        "ClientSideTargetResolution": {
            "adapter": {
                "config": {
                    "inbounds": {
                        "myReuseComp": {
                            "semanticObject": "Reusecomp",
                            "action": "manage",
                            "title": "Reuse Component",
                            "signature": {
                                "parameters": {},
                                "additionalParameters": "allowed"
                            },
                            "resolutionResult": {
                                "applicationType": "URL",
                                "additionalInformation": "SAPUI5.Component=demo.suresh.reusecomp",
                                "url": "reusecomp"
                            }
                        },
                        "myCompConsumer": {
                            "semanticObject": "Consumer",
                            "action": "manage",
                            "title": "Component Consumer",
                            "signature": {
                                "parameters": {},
                                "additionalParameters": "allowed"
                            },
                            "resolutionResult": {
                                "applicationType": "URL",
                                "additionalInformation": "SAPUI5.Component=demo.suresh.compconsumer",
                                "url": "compconsumer"
                            }
                        },
                        "myCompConsumer02": {
                            "semanticObject": "Consumer02",
                            "action": "manage",
                            "title": "Component Consumer 02",
                            "signature": {
                                "parameters": {},
                                "additionalParameters": "allowed"
                            },
                            "resolutionResult": {
                                "applicationType": "URL",
                                "additionalInformation": "SAPUI5.Component=demo.suresh.compconsumer",
                                "url": "compconsumer02"
                            }
                        }
                    }
                }
            }
        }
    }
}